LICENSE
MANIFEST.in
README.rst
setup.cfg
setup.py
/home/fstagni/pyDevs/pyGSI/src/util.c
/home/fstagni/pyDevs/pyGSI/src/crypto/asn1.c
/home/fstagni/pyDevs/pyGSI/src/crypto/crypto.c
/home/fstagni/pyDevs/pyGSI/src/crypto/netscape_spki.c
/home/fstagni/pyDevs/pyGSI/src/crypto/pkcs12.c
/home/fstagni/pyDevs/pyGSI/src/crypto/pkcs7.c
/home/fstagni/pyDevs/pyGSI/src/crypto/pkey.c
/home/fstagni/pyDevs/pyGSI/src/crypto/x509.c
/home/fstagni/pyDevs/pyGSI/src/crypto/x509CRL.c
/home/fstagni/pyDevs/pyGSI/src/crypto/x509ext.c
/home/fstagni/pyDevs/pyGSI/src/crypto/x509name.c
/home/fstagni/pyDevs/pyGSI/src/crypto/x509req.c
/home/fstagni/pyDevs/pyGSI/src/crypto/x509store.c
/home/fstagni/pyDevs/pyGSI/src/rand/rand.c
/home/fstagni/pyDevs/pyGSI/src/ssl/connection.c
/home/fstagni/pyDevs/pyGSI/src/ssl/context.c
/home/fstagni/pyDevs/pyGSI/src/ssl/gsi.c
/home/fstagni/pyDevs/pyGSI/src/ssl/session.c
/home/fstagni/pyDevs/pyGSI/src/ssl/ssl.c
/home/fstagni/pyDevs/pyGSI/src/ssl/thread_safe.c
GSI/__init__.py
GSI/tsafe.py
GSI/version.py
GSI.egg-info/PKG-INFO
GSI.egg-info/SOURCES.txt
GSI.egg-info/dependency_links.txt
GSI.egg-info/not-zip-safe
GSI.egg-info/top_level.txt
src/pymemcompat.h
src/util.c
src/util.h
src/crypto/asn1.c
src/crypto/asn1.h
src/crypto/crypto.c
src/crypto/crypto.h
src/crypto/netscape_spki.c
src/crypto/netscape_spki.h
src/crypto/pkcs12.c
src/crypto/pkcs12.h
src/crypto/pkcs7.c
src/crypto/pkcs7.h
src/crypto/pkey.c
src/crypto/pkey.h
src/crypto/x509.c
src/crypto/x509.h
src/crypto/x509CRL.c
src/crypto/x509CRL.h
src/crypto/x509ext.c
src/crypto/x509ext.h
src/crypto/x509name.c
src/crypto/x509name.h
src/crypto/x509req.c
src/crypto/x509req.h
src/crypto/x509store.c
src/crypto/x509store.h
src/rand/rand.c
src/ssl/connection.c
src/ssl/connection.h
src/ssl/context.c
src/ssl/context.h
src/ssl/gsi.c
src/ssl/gsi.h
src/ssl/session.c
src/ssl/session.h
src/ssl/ssl.c
src/ssl/ssl.h
src/ssl/thread_safe.c
src/ssl/thread_safe.h