Metadata-Version: 1.2
Name: GSI
Version: 0.6.5
Summary: Python wrapper module around the OpenSSL library
Home-page: https://github.com/DIRACGrid/pyGSI
Author: Adrian Casajus
Author-email: adria@ecm.ub.es
License: GPLv3
Platform: UNKNOWN
Classifier: Development Status :: 5 - Production/Stable
Classifier: Intended Audience :: Developers
Classifier: Programming Language :: Python :: 2
Classifier: Programming Language :: Python :: 2.7
Requires-Python: >=2.7
